chATLAS_Chains/__init__.py
chATLAS_Chains/log.py
chATLAS_Chains/vectorstore.py
chATLAS_Chains/chains/__init__.py
chATLAS_Chains/chains/advanced.py
chATLAS_Chains/chains/basic.py
chATLAS_Chains/chains/basic_graph.py
chATLAS_Chains/chains/enhanced_agentic_graph.py
chATLAS_Chains/chains/websearch_retrieval_chain.py
chATLAS_Chains/documents/rerank.py
chATLAS_Chains/documents/rrf.py
chATLAS_Chains/llm/__init__.py
chATLAS_Chains/llm/groq.py
chATLAS_Chains/llm/model_selection.py
chATLAS_Chains/prompt/__init__.py
chATLAS_Chains/prompt/doc_joiners.py
chATLAS_Chains/prompt/starters.py
chATLAS_Chains/query/query_rewriting.py
chATLAS_Chains/search/__init__.py
chATLAS_Chains/search/basic.py
chATLAS_Chains/utils/__init__.py
chATLAS_Chains/utils/doc_utils.py
chatlas_chains-0.1.6.dist-info/licenses/LICENSE
tests/__init__.py
tests/conftest.py
tests/test_chains.py
tests/test_groq.py
tests/test_llm.py
tests/test_rrf.py
tests/test_search.py
tests/test_utils.py
chatlas_chains-0.1.6.dist-info/METADATA
chatlas_chains-0.1.6.dist-info/WHEEL
chatlas_chains-0.1.6.dist-info/top_level.txt
chatlas_chains-0.1.6.dist-info/RECORD
