Metadata-Version: 2.4
Name: chATLAS_Chains
Version: 0.1.6
Summary: A modular Python package for implementing Retrieval Augmented Generation chains for the chATLAS project.
Author-email: Joe Egan <joseph.caimin.egan@cern.ch>
License: Apache-2.0
Project-URL: Homepage, https://gitlab.cern.ch/atlasml/chatlas/chatlas-packages/
Classifier: Programming Language :: Python :: 3
Classifier: License :: OSI Approved :: Apache Software License
Classifier: Operating System :: OS Independent
Requires-Python: >=3.11
License-File: LICENSE
Requires-Dist: chatlas-embed>=0.1.19
Requires-Dist: langchain~=0.3.3
Requires-Dist: langchain_core
Requires-Dist: langchain_openai
Requires-Dist: langgraph
Requires-Dist: sentence-transformers>=3.0.0
Requires-Dist: tiktoken
Requires-Dist: pinecone
Requires-Dist: torch==2.2.1
Requires-Dist: chatlas-embed
Requires-Dist: psycopg2-binary>=2.9.10
Dynamic: license-file
